LICENSE
MANIFEST.in
README.rst
setup.py
bee_django_course/__init__.py
bee_django_course/admin.py
bee_django_course/apps.py
bee_django_course/cc.py
bee_django_course/config.py
bee_django_course/context_processors.py
bee_django_course/csv_tools.py
bee_django_course/decorators.py
bee_django_course/dt.py
bee_django_course/exports.py
bee_django_course/forms.py
bee_django_course/gensee.py
bee_django_course/models.py
bee_django_course/qiniu_api.py
bee_django_course/signals.py
bee_django_course/tests.py
bee_django_course/urls.py
bee_django_course/utils.py
bee_django_course/views.py
bee_django_course.egg-info/PKG-INFO
bee_django_course.egg-info/SOURCES.txt
bee_django_course.egg-info/dependency_links.txt
bee_django_course.egg-info/requires.txt
bee_django_course.egg-info/top_level.txt
bee_django_course/management/__init__.py
bee_django_course/management/__init__.pyc
bee_django_course/management/commands/__init__.py
bee_django_course/management/commands/__init__.pyc
bee_django_course/management/commands/auto_pass_ucs.py
bee_django_course/management/commands/auto_pass_ucs.pyc
bee_django_course/management/commands/delete_assignment_image.py
bee_django_course/management/commands/delete_user_live.py
bee_django_course/management/commands/delete_user_live.pyc
bee_django_course/management/commands/gensee_vod_sync.py
bee_django_course/migrations/0001_initial.py
bee_django_course/migrations/0001_initial.pyc
bee_django_course/migrations/0002_auto_20171218_1738.py
bee_django_course/migrations/0002_auto_20171218_1738.pyc
bee_django_course/migrations/0003_section.py
bee_django_course/migrations/0003_section.pyc
bee_django_course/migrations/0004_auto_20180108_1638.py
bee_django_course/migrations/0004_auto_20180108_1638.pyc
bee_django_course/migrations/0005_auto_20180108_1640.py
bee_django_course/migrations/0005_auto_20180108_1640.pyc
bee_django_course/migrations/0006_auto_20180108_1846.py
bee_django_course/migrations/0006_auto_20180108_1846.pyc
bee_django_course/migrations/0007_auto_20180317_0917.py
bee_django_course/migrations/0007_auto_20180317_0917.pyc
bee_django_course/migrations/0008_auto_20180317_0958.py
bee_django_course/migrations/0008_auto_20180317_0958.pyc
